PyHiveHere-0.6.1.dist-info/DESCRIPTION.rst
PyHiveHere-0.6.1.dist-info/METADATA
PyHiveHere-0.6.1.dist-info/RECORD
PyHiveHere-0.6.1.dist-info/WHEEL
PyHiveHere-0.6.1.dist-info/entry_points.txt
PyHiveHere-0.6.1.dist-info/metadata.json
PyHiveHere-0.6.1.dist-info/top_level.txt
TCLIService/TCLIService.py
TCLIService/__init__.py
TCLIService/constants.py
TCLIService/ttypes.py
pyhive/__init__.py
pyhive/common.py
pyhive/exc.py
pyhive/hive.py
pyhive/presto.py
pyhive/sqlalchemy_hive.py
pyhive/sqlalchemy_presto.py
pyhivehere/__init__.py
pyhivehere/common.py
pyhivehere/exc.py
pyhivehere/hive.py
pyhivehere/presto.py
pyhivehere/sqlalchemy_hive.py
pyhivehere/sqlalchemy_presto.py
