Metadata-Version: 2.0
Name: PyHiveHere
Version: 0.6.1
Summary: Python interface to Hive
Home-page: https://github.com/dropbox/PyHive
Author: Jing Wang
Author-email: jing@dropbox.com
License: Apache License, Version 2.0
Platform: UNKNOWN
Classifier: Intended Audience :: Developers
Classifier: License :: OSI Approved :: Apache Software License
Classifier: Operating System :: OS Independent
Classifier: Topic :: Database :: Front-Ends
Requires-Dist: future
Requires-Dist: python-dateutil
Provides-Extra: hive
Requires-Dist: sasl (>=0.2.1); extra == 'hive'
Requires-Dist: thrift (>=0.10.0); extra == 'hive'
Requires-Dist: thrift-sasl (>=0.1.0); extra == 'hive'
Provides-Extra: presto
Requires-Dist: requests (>=1.0.0); extra == 'presto'
Provides-Extra: sqlalchemy
Requires-Dist: sqlalchemy (>=0.8.7); extra == 'sqlalchemy'
